MANIFEST.in
README.md
VERSION
setup.py
../LICENSE
kubectl_kadalu/__init__.py
kubectl_kadalu/install.py
kubectl_kadalu/main.py
kubectl_kadalu/storage_add.py
kubectl_kadalu/utils.py
kubectl_kadalu.egg-info/PKG-INFO
kubectl_kadalu.egg-info/SOURCES.txt
kubectl_kadalu.egg-info/dependency_links.txt
kubectl_kadalu.egg-info/entry_points.txt
kubectl_kadalu.egg-info/not-zip-safe
kubectl_kadalu.egg-info/requires.txt
kubectl_kadalu.egg-info/top_level.txt